{
  "global": {
    "140": {
      "value": "140%",
      "type": "lineHeights"
    },
    "150": {
      "value": "150%",
      "type": "lineHeights"
    },
    "160": {
      "value": "160%",
      "type": "lineHeights"
    },
    "baseSpacing": {
      "value": "4",
      "type": "spacing"
    },
    "space-1": {
      "value": "{baseSpacing}",
      "type": "spacing"
    },
    "space-2": {
      "value": "{space-1}+{baseSpacing}",
      "type": "spacing"
    },
    "space-3": {
      "value": "{space-2}+{baseSpacing}",
      "type": "spacing"
    },
    "space-4": {
      "value": "{space-3}+{baseSpacing}",
      "type": "spacing"
    },
    "space-5": {
      "value": "{space-4}+{baseSpacing}",
      "type": "spacing"
    },
    "space-6": {
      "value": "{space-5}+{baseSpacing}",
      "type": "spacing"
    },
    "space-7": {
      "value": "{space-6}+{baseSpacing}",
      "type": "spacing"
    },
    "space-8": {
      "value": "{space-7}+{baseSpacing}",
      "type": "spacing"
    },
    "space-9": {
      "value": "{space-8}+{baseSpacing}",
      "type": "spacing"
    },
    "space-10": {
      "value": "{space-9}+{baseSpacing}",
      "type": "spacing"
    },
    "space-11": {
      "value": "{space-10}+{baseSpacing}",
      "type": "spacing"
    },
    "space-12": {
      "value": "{space-11}+{baseSpacing}",
      "type": "spacing"
    },
    "space-13": {
      "value": "{space-12}+{baseSpacing}",
      "type": "spacing"
    },
    "space-14": {
      "value": "{space-13}+{baseSpacing}",
      "type": "spacing"
    },
    "space-15": {
      "value": "{space-14}+{baseSpacing}",
      "type": "spacing"
    },
    "space-16": {
      "value": "{space-15}+{baseSpacing}",
      "type": "spacing"
    },
    "white": {
      "value": "#ffffff",
      "type": "color"
    },
    "black": {
      "value": "#000000",
      "type": "color"
    },
    "grey": {
      "100": {
        "value": "#e1e1e1",
        "type": "color"
      },
      "200": {
        "value": "#c4c4c4",
        "type": "color"
      },
      "300": {
        "value": "#a6a6a6",
        "type": "color"
      },
      "400": {
        "value": "#898989",
        "type": "color"
      },
      "500": {
        "value": "#6b6b6b",
        "type": "color"
      },
      "600": {
        "value": "#565656",
        "type": "color"
      },
      "700": {
        "value": "#404040",
        "type": "color"
      },
      "800": {
        "value": "#2b2b2b",
        "type": "color"
      },
      "900": {
        "value": "#151515",
        "type": "color"
      }
    },
    "blue": {
      "100": {
        "value": "#ccd6f5",
        "type": "color"
      },
      "200": {
        "value": "#99adeb",
        "type": "color"
      },
      "300": {
        "value": "#6685e0",
        "type": "color"
      },
      "400": {
        "value": "#335cd6",
        "type": "color"
      },
      "500": {
        "value": "#0033cc",
        "type": "color"
      },
      "600": {
        "value": "#0029a3",
        "type": "color"
      },
      "700": {
        "value": "#001f7a",
        "type": "color"
      },
      "800": {
        "value": "#001452",
        "type": "color"
      },
      "900": {
        "value": "#000a29",
        "type": "color"
      }
    },
    "red": {
      "100": {
        "value": "#ebcccc",
        "type": "color"
      },
      "200": {
        "value": "#d69999",
        "type": "color"
      },
      "300": {
        "value": "#c26666",
        "type": "color"
      },
      "400": {
        "value": "#ad3333",
        "type": "color"
      },
      "500": {
        "value": "#990000",
        "type": "color"
      },
      "600": {
        "value": "#7a0000",
        "type": "color"
      },
      "700": {
        "value": "#5c0000",
        "type": "color"
      },
      "800": {
        "value": "#3d0000",
        "type": "color"
      },
      "900": {
        "value": "#1f0000",
        "type": "color"
      }
    },
    "yellow": {
      "100": {
        "value": "#fff4cf",
        "type": "color"
      },
      "200": {
        "value": "#ffea9e",
        "type": "color"
      },
      "300": {
        "value": "#ffdf6e",
        "type": "color"
      },
      "400": {
        "value": "#ffd43d",
        "type": "color"
      },
      "500": {
        "value": "#ffca0d",
        "type": "color"
      },
      "600": {
        "value": "#cca10a",
        "type": "color"
      },
      "700": {
        "value": "#997908",
        "type": "color"
      },
      "800": {
        "value": "#665105",
        "type": "color"
      },
      "900": {
        "value": "#332803",
        "type": "color"
      }
    },
    "green": {
      "100": {
        "value": "#cfe4dc",
        "type": "color"
      },
      "200": {
        "value": "#9fc9ba",
        "type": "color"
      },
      "300": {
        "value": "#6fad97",
        "type": "color"
      },
      "400": {
        "value": "#3f9274",
        "type": "color"
      },
      "500": {
        "value": "#0f7752",
        "type": "color"
      },
      "600": {
        "value": "#0c5f41",
        "type": "color"
      },
      "700": {
        "value": "#094731",
        "type": "color"
      },
      "800": {
        "value": "#063021",
        "type": "color"
      },
      "900": {
        "value": "#031810",
        "type": "color"
      }
    },
    "info": {
      "Error": {
        "value": "{red.500}",
        "type": "color"
      },
      "Success": {
        "value": "{green.500}",
        "type": "color"
      },
      "Warning": {
        "value": "{yellow.500}",
        "type": "color"
      }
    },
    "Accent": {
      "value": "{blue.500}",
      "type": "color"
    },
    "Pretendard": {
      "value": "Pretendard",
      "type": "fontFamilies",
      "Heading": {
        "Medium": {
          "value": {
            "fontFamily": "{Pretendard}",
            "fontWeight": "{Bold}",
            "lineHeight": "{140}",
            "fontSize": "{medium}",
            "letterSpacing": "none",
            "paragraphSpacing": "none",
            "paragraphIndent": "none",
            "textDecoration": "none",
            "textCase": "none"
          },
          "type": "typography"
        },
        "Large": {
          "value": {
            "fontFamily": "{Pretendard}",
            "fontWeight": "{Bold}",
            "lineHeight": "{140}",
            "fontSize": "{large}",
            "letterSpacing": "none",
            "paragraphSpacing": "none",
            "paragraphIndent": "none",
            "textDecoration": "none",
            "textCase": "none"
          },
          "type": "typography"
        },
        "XL": {
          "value": {
            "fontFamily": "{Pretendard}",
            "fontWeight": "{Bold}",
            "lineHeight": "{140}",
            "fontSize": "{XL}",
            "letterSpacing": "none",
            "paragraphSpacing": "none",
            "paragraphIndent": "none",
            "textDecoration": "none",
            "textCase": "none"
          },
          "type": "typography"
        },
        "XXL": {
          "value": {
            "fontFamily": "{Pretendard}",
            "fontWeight": "{Bold}",
            "lineHeight": "{140}",
            "fontSize": "{XXL}",
            "letterSpacing": "none",
            "paragraphSpacing": "none",
            "paragraphIndent": "none",
            "textDecoration": "none",
            "textCase": "none"
          },
          "type": "typography"
        },
        "XXXL": {
          "value": {
            "fontFamily": "{Pretendard}",
            "fontWeight": "{Bold}",
            "lineHeight": "{140}",
            "fontSize": "{XXXL}",
            "letterSpacing": "none",
            "paragraphSpacing": "none",
            "paragraphIndent": "none",
            "textDecoration": "none",
            "textCase": "none"
          },
          "type": "typography"
        }
      },
      "Label": {
        "Small": {
          "value": {
            "fontFamily": "{Pretendard}",
            "fontWeight": "{SemiBold}",
            "lineHeight": "{150}",
            "fontSize": "{small}",
            "letterSpacing": "none",
            "paragraphSpacing": "none",
            "paragraphIndent": "none",
            "textDecoration": "none",
            "textCase": "none"
          },
          "type": "typography"
        },
        "Medium": {
          "value": {
            "fontFamily": "{Pretendard}",
            "fontWeight": "{SemiBold}",
            "lineHeight": "{150}",
            "fontSize": "{medium}",
            "letterSpacing": "none",
            "paragraphSpacing": "none",
            "paragraphIndent": "none",
            "textDecoration": "none",
            "textCase": "none"
          },
          "type": "typography"
        },
        "Large": {
          "value": {
            "fontFamily": "{Pretendard}",
            "fontWeight": "{SemiBold}",
            "lineHeight": "{150}",
            "fontSize": "{large}",
            "letterSpacing": "none",
            "paragraphSpacing": "none",
            "paragraphIndent": "none",
            "textDecoration": "none",
            "textCase": "none"
          },
          "type": "typography"
        },
        "XL": {
          "value": {
            "fontFamily": "{Pretendard}",
            "fontWeight": "{SemiBold}",
            "lineHeight": "{150}",
            "fontSize": "{XL}",
            "letterSpacing": "none",
            "paragraphSpacing": "none",
            "paragraphIndent": "none",
            "textDecoration": "none",
            "textCase": "none"
          },
          "type": "typography"
        },
        "XXL": {
          "value": {
            "fontFamily": "{Pretendard}",
            "fontWeight": "{SemiBold}",
            "lineHeight": "{150}",
            "fontSize": "{XXL}",
            "letterSpacing": "none",
            "paragraphSpacing": "none",
            "paragraphIndent": "none",
            "textDecoration": "none",
            "textCase": "none"
          },
          "type": "typography"
        }
      },
      "Paragraph": {
        "Small": {
          "value": {
            "fontFamily": "{Pretendard}",
            "fontWeight": "{Regular}",
            "lineHeight": "{160}",
            "fontSize": "{small}",
            "letterSpacing": "none",
            "paragraphSpacing": "none",
            "paragraphIndent": "none",
            "textDecoration": "none",
            "textCase": "none"
          },
          "type": "typography"
        },
        "Medium": {
          "value": {
            "fontFamily": "{Pretendard}",
            "fontWeight": "{Regular}",
            "lineHeight": "{160}",
            "fontSize": "{medium}",
            "letterSpacing": "none",
            "paragraphSpacing": "none",
            "paragraphIndent": "none",
            "textDecoration": "none",
            "textCase": "none"
          },
          "type": "typography"
        },
        "Large": {
          "value": {
            "fontFamily": "{Pretendard}",
            "fontWeight": "{Regular}",
            "lineHeight": "{160}",
            "fontSize": "{large}",
            "letterSpacing": "none",
            "paragraphSpacing": "none",
            "paragraphIndent": "none",
            "textDecoration": "none",
            "textCase": "none"
          },
          "type": "typography"
        },
        "XL": {
          "value": {
            "fontFamily": "{Pretendard}",
            "fontWeight": "{Regular}",
            "lineHeight": "{160}",
            "fontSize": "{XL}",
            "letterSpacing": "none",
            "paragraphSpacing": "none",
            "paragraphIndent": "none",
            "textDecoration": "none",
            "textCase": "none"
          },
          "type": "typography"
        },
        "XXL": {
          "value": {
            "fontFamily": "{Pretendard}",
            "fontWeight": "{Regular}",
            "lineHeight": "{160}",
            "fontSize": "{XXL}",
            "letterSpacing": "none",
            "paragraphSpacing": "none",
            "paragraphIndent": "none",
            "textDecoration": "none",
            "textCase": "none"
          },
          "type": "typography"
        }
      }
    },
    "Regular": {
      "value": "Regular",
      "type": "fontWeights"
    },
    "SemiBold": {
      "value": "SemiBold",
      "type": "fontWeights"
    },
    "Bold": {
      "value": "Bold",
      "type": "fontWeights"
    },
    "base": {
      "value": "16",
      "type": "fontSizes"
    },
    "scale": {
      "value": "1.333",
      "type": "sizing"
    },
    "small": {
      "value": "{medium}/{scale}",
      "type": "fontSizes"
    },
    "medium": {
      "value": "{base}",
      "type": "fontSizes"
    },
    "large": {
      "value": "{medium}*{scale}",
      "type": "fontSizes"
    },
    "XL": {
      "value": "{large}*{scale}",
      "type": "fontSizes"
    },
    "XXL": {
      "value": "{XL}*{scale}",
      "type": "fontSizes"
    },
    "XXXL": {
      "value": "{XXL}*{scale}",
      "type": "fontSizes"
    },
    "button": {
      "value": "20",
      "type": "borderRadius"
    },
    "Space Grotesk": {
      "value": "Space Grotesk",
      "type": "fontFamilies"
    }
  },
  "light": {
    "Primary": {
      "value": "{black}",
      "type": "color"
    },
    "Secondary": {
      "value": "{white}",
      "type": "color"
    },
    "Tertiary": {
      "value": "#f5f5f5",
      "type": "color"
    },
    "contentPrimary": {
      "value": "black",
      "type": "color"
    }
  },
  "dark": {
    "Primary": {
      "value": "{white}",
      "type": "color"
    },
    "Secondary": {
      "value": "{black}",
      "type": "color"
    },
    "Tertiary": {
      "value": "{grey.800}",
      "type": "color"
    }
  },
  "$themes": [],
  "$metadata": {
    "tokenSetOrder": [
      "global",
      "light",
      "dark"
    ]
  }
}